aistrigh_nlp/__init__.py
aistrigh_nlp/aistrigh.py
aistrigh_nlp/apply_mutations.py
aistrigh_nlp/demutate_corpus.py
aistrigh_nlp/demutate_window.py
aistrigh_nlp/predict_inference.py
aistrigh_nlp/utils.py
aistrigh_nlp-0.1.0.dist-info/LICENSE
aistrigh_nlp-0.1.0.dist-info/METADATA
aistrigh_nlp-0.1.0.dist-info/WHEEL
aistrigh_nlp-0.1.0.dist-info/entry_points.txt
aistrigh_nlp-0.1.0.dist-info/top_level.txt
aistrigh_nlp-0.1.0.dist-info/RECORD
