Metadata-Version: 2.1
Name: aistrigh-nlp
Version: 0.1.0
Summary: AistrighNLP - A collection of NLP tools for Irish
Home-page: https://github.com/JustCunn/AistrighNLP
Author: Justin Cunningham
Author-email: justincunningham@patriciansecondary.com
License: MIT
Platform: UNKNOWN
Classifier: Programming Language :: Python :: 3
Classifier: License :: OSI Approved :: MIT License
Classifier: Operating System :: Unix
